[{"fullName":"mathias","password":"$2b$10$JlKD3DZww8XKqqTaue229upWvUFE7GcAL0sgY5puZL96V23WcXdwC"},{"fullName":"mathias1","password":"$2b$10$1tlFt06tn1iCctO0KBhSBeOeL0n.WGHu8ZjldU.5UMy7sQ10V2Zpe"},{"fullName":"mathias1","password":"$2b$10$f1lzT9LPh9MQLdD8W//9aeWp2bCc9n.e2o0JN2L2VUhhxzxDvtpxm"},{"fullName":"mathias1","password":"$2b$10$kmPeDLdgy1HBcEc1PYTIae3iW4eVCvCM5qgQiJVoOfaYJD48Y4Yly"},{"fullName":"mathias4","password":"$2b$10$REZ6pHe5RtGN1JelWf5/KOOgzQf/R9VbdSayTFEz6z0mIRWz8PYMS"},{"fullName":"mathias3","password":"$2b$10$bnMvhC6QebcXIEN7S4kmN.94QwMB722DvuEXfPg3X.C6NcjcUnZGe"},{"fullName":"mathias3","password":"$2b$10$qBAQEt.JG1u9AechjRtCY.GEqxNrZSzhLfUB3FoZEwjrtXDXP4fGC"},{"fullName":"mathias4","password":"$2b$10$C3.MdUEjmPddUkiVHxUtMeylOQ7NKe0d0.O9QIiPgNbuy/BbO7ZmC"},{"fullName":"mathias4","password":"$2b$10$x852FquCoJjEGmTzOH4mduSqyBUDueYSBQ4Z58jeGpSSt9p89rYc2"},{"fullName":"mathias5","password":"$2b$10$4oy2Rc7hUwZVUolqVNzeCewfKtnembV67mTyn42nHQ3fOPdkx0Gtu"},{"fullName":"mathias6","password":"$2b$10$jY6sKJpTHEjGAQ77dZCLke3sTp03EnJWaXIPmZfdmDdDRsmEvjH4C"},{"fullName":"mathias7","password":"$2b$10$8L8Jw/BaljPG82iN5sIgOeiUf3F5pkcxSZ1GmCzusvTQDpUvB6saa"},{"fullName":"mathias9","password":"$2b$10$u7DPmnGiHuZrgLOIslOdSOTa9Cpg8uKp4UWpvSyjortAZINZ9b8b2"},{"fullName":"mathias10","password":"$2b$10$t6KyRQlrhRORrm/MGup6K.UcwevoYCY/.f5m8Dod.KXkC6s2VAD0W"},{"fullName":"mathias11","password":"$2b$10$Ja2IeudiVA5mpeBVa1ovv.jW9HaR5FKypJyDItxo4yzPivCsVeysm"},{"fullName":"mathias12","password":"$2b$10$tlIVbSqsflK1aK60sbOACOoSb7bq5MU4Ru4/vJDgDWRHn9cFfBCtO"},{"fullName":"mathias13","password":"$2b$10$jhjVLMum06cTtI5E9HzPEe7thVN1MW5Rsj0efYDWPXT885LZ.6etO"},{"fullName":"mathias14","password":"$2b$10$zB0kdXJF/y7YNAUckO7C.ebtqhyNTS7.e2W81MYJ.06etsfHAmFFq"},{"fullName":"mathias15","password":"$2b$10$laXIjqMwiVkV25GDH9jsl.c28f.voHB6iohbDRE91h4oJcaDwH4hK"},{"fullName":"mathias16","password":"$2b$10$i8.MPky24ngHZF1QD3qFdeAc0c0D2Bzld9Tu2N0CmdMNvqX2sFteK"},{"fullName":"mathias17","password":"$2b$10$bVXHywZ/Ygo/9MEUHKFi5OY9NImu7KUEYLZBDqjN6tRA10rj4D/b6"},{"fullName":"mathias18","password":"$2b$10$mVweTH9Pu43xq7zk0/vnuevzPyBcMpkrmlEvTl2P86Hk1/fNl.EVW"},{"fullName":"mathias19","password":"$2b$10$kCtwLkBpr4UXGLt/LmE3vuGeGowo.Qz3VyLTOdCkUm7pBt3.H5Lhi"},{"fullName":"mathias20","password":"$2b$10$aEWb.e8IDpw3GLcpe/Rn9.konB0uNmTkHjhiTG5L5U8gutIyce0Oi"}]